cygnusdatautils/__init__.py
cygnusdatautils/database_utils.py
cygnusdatautils/sharefile.py
cygnusdatautils-0.2.dist-info/METADATA
cygnusdatautils-0.2.dist-info/WHEEL
cygnusdatautils-0.2.dist-info/top_level.txt
cygnusdatautils-0.2.dist-info/RECORD
